dias_uteis.py
dias_uteis-0.1.14.dist-info/LICENSE
dias_uteis-0.1.14.dist-info/METADATA
dias_uteis-0.1.14.dist-info/WHEEL
dias_uteis-0.1.14.dist-info/RECORD
