Metadata-Version: 2.3
Name: dias-uteis
Version: 0.1.14
Summary: Ferramentas para cálculos de dias úteis no calendário brasileiro.
Author: renanmoretto
Author-email: himynameisrenan@outlook.com
Requires-Python: >=3.6,<4.0
Classifier: Programming Language :: Python :: 3
Classifier: Programming Language :: Python :: 3.6
Classifier: Programming Language :: Python :: 3.7
Classifier: Programming Language :: Python :: 3.8
Classifier: Programming Language :: Python :: 3.9
Classifier: Programming Language :: Python :: 3.10
Classifier: Programming Language :: Python :: 3.11
Classifier: Programming Language :: Python :: 3.12
Classifier: Programming Language :: Python :: 3.13
Project-URL: Repository, https://github.com/renanmoretto/dias_uteis
